maxondevelop_package/__init__.py
maxondevelop_package/__main__.py
maxondevelop_package/cli.py
maxondevelop_package-0.0.1.dist-info/METADATA
maxondevelop_package-0.0.1.dist-info/WHEEL
maxondevelop_package-0.0.1.dist-info/entry_points.txt
maxondevelop_package-0.0.1.dist-info/top_level.txt
maxondevelop_package-0.0.1.dist-info/RECORD
