Metadata-Version: 2.1
Name: maxondevelop-package
Version: 0.0.1
Summary: Bref description
Home-page: http://maxondevelop-package.com
Author: Maxondevelop
Author-email: timetotime828@gmail.com
License: MIT
Project-URL: Documentation, http://docs.com
Project-URL: Source, http://github.com
Classifier: Development Status :: 3 - Alpha
Classifier: Intended Audience :: Developers
Classifier: Programming Language :: Python :: 3.10
Classifier: Programming Language :: Python :: 3.11
Classifier: Programming Language :: Python :: 3.12
Classifier: Topic :: Utilities
Requires-Python: >=3.10,<=3.12
Requires-Dist: requests
Requires-Dist: pandas >=2.0
Provides-Extra: excel
Requires-Dist: openpyxl ; extra == 'excel'
